{"member": [{"member": [{"member": [{"member": [], "type": {"Group": null, "Item": null, "Page": null, "Paragraph": null, "Table": null, "Column": null, "Row": null, "Cell": true, "List": null, "ListItem": null}, "label": null, "style": {"Emphasize": true, "Enumerate": null, "ColMajor": null, "RowMajor": null, "GrpSpan": null, "LineSpan": true, "GrpSpanBr": null, "LineSpanBr": null}, "dimension": null, "link": {}, "local": {"GrpSkip": null, "LineSkip": null, "GrpSpan": null, "LineSpan": null}}, {"member": [], "type": {"Group": null, "Item": null, "Page": null, "Paragraph": null, "Table": null, "Column": null, "Row": null, "Cell": true, "List": null, "ListItem": null}, "label": null, "style": {"Emphasize": true, "Enumerate": null, "ColMajor": null, "RowMajor": null, "GrpSpan": null, "LineSpan": true, "GrpSpanBr": null, "LineSpanBr": null}, "dimension": null, "link": {}, "local": {"GrpSkip": null, "LineSkip": null, "GrpSpan": null, "LineSpan": null}}, {"member": [], "type": {"Group": null, "Item": null, "Page": null, "Paragraph": null, "Table": null, "Column": null, "Row": null, "Cell": true, "List": null, "ListItem": null}, "label": "males", "style": {"Emphasize": true, "Enumerate": null, "ColMajor": null, "RowMajor": null, "GrpSpan": null, "LineSpan": null, "GrpSpanBr": null, "LineSpanBr": null}, "dimension": null, "link": {}, "local": {"GrpSkip": null, "LineSkip": null, "GrpSpan": null, "LineSpan": null}}, {"member": [], "type": {"Group": null, "Item": null, "Page": null, "Paragraph": null, "Table": null, "Column": null, "Row": null, "Cell": true, "List": null, "ListItem": null}, "label": "females", "style": {"Emphasize": true, "Enumerate": null, "ColMajor": null, "RowMajor": null, "GrpSpan": null, "LineSpan": true, "GrpSpanBr": null, "LineSpanBr": null}, "dimension": null, "link": {}, "local": {"GrpSkip": null, "LineSkip": null, "GrpSpan": null, "LineSpan": null}}, {"member": [], "type": {"Group": null, "Item": null, "Page": null, "Paragraph": null, "Table": null, "Column": null, "Row": null, "Cell": true, "List": null, "ListItem": null}, "label": "females", "style": {"Emphasize": true, "Enumerate": null, "ColMajor": null, "RowMajor": null, "GrpSpan": null, "LineSpan": true, "GrpSpanBr": null, "LineSpanBr": null}, "dimension": null, "link": {}, "local": {"GrpSkip": null, "LineSkip": null, "GrpSpan": null, "LineSpan": null}}], "type": {"Group": null, "Item": null, "Page": null, "Paragraph": null, "Table": null, "Column": true, "Row": null, "Cell": null, "List": null, "ListItem": null}, "label": null, "style": {"Emphasize": null, "Enumerate": true, "ColMajor": null, "RowMajor": null, "GrpSpan": null, "LineSpan": null, "GrpSpanBr": null, "LineSpanBr": null}, "dimension": null, "link": {}, "local": {"GrpSkip": null, "LineSkip": null, "GrpSpan": null, "LineSpan": null}}, {"member": [{"member": [], "type": {"Group": null, "Item": null, "Page": null, "Paragraph": null, "Table": null, "Column": null, "Row": null, "Cell": true, "List": null, "ListItem": null}, "label": "Average", "style": {"Emphasize": true, "Enumerate": null, "ColMajor": null, "RowMajor": null, "GrpSpan": true, "LineSpan": null, "GrpSpanBr": null, "LineSpanBr": null}, "dimension": null, "link": {}, "local": {"GrpSkip": null, "LineSkip": null, "GrpSpan": null, "LineSpan": null}}, {"member": [], "type": {"Group": null, "Item": null, "Page": null, "Paragraph": null, "Table": null, "Column": null, "Row": null, "Cell": true, "List": null, "ListItem": null}, "label": "height", "style": {"Emphasize": true, "Enumerate": null, "ColMajor": null, "RowMajor": null, "GrpSpan": null, "LineSpan": null, "GrpSpanBr": null, "LineSpanBr": null}, "dimension": null, "link": {}, "local": {"GrpSkip": null, "LineSkip": null, "GrpSpan": null, "LineSpan": null}}, {"member": [], "type": {"Group": null, "Item": null, "Page": null, "Paragraph": null, "Table": null, "Column": null, "Row": null, "Cell": true, "List": null, "ListItem": null}, "label": "1.9", "style": {"Emphasize": null, "Enumerate": null, "ColMajor": null, "RowMajor": null, "GrpSpan": null, "LineSpan": null, "GrpSpanBr": null, "LineSpanBr": null}, "dimension": null, "link": {}, "local": {"GrpSkip": null, "LineSkip": null, "GrpSpan": null, "LineSpan": null}}, {"member": [], "type": {"Group": null, "Item": null, "Page": null, "Paragraph": null, "Table": null, "Column": null, "Row": null, "Cell": true, "List": null, "ListItem": null}, "label": "1.7", "style": {"Emphasize": null, "Enumerate": null, "ColMajor": null, "RowMajor": null, "GrpSpan": null, "LineSpan": null, "GrpSpanBr": null, "LineSpanBr": null}, "dimension": null, "link": {}, "local": {"GrpSkip": null, "LineSkip": null, "GrpSpan": null, "LineSpan": null}}], "type": {"Group": null, "Item": null, "Page": null, "Paragraph": null, "Table": null, "Column": true, "Row": null, "Cell": null, "List": null, "ListItem": null}, "label": null, "style": {"Emphasize": null, "Enumerate": true, "ColMajor": null, "RowMajor": null, "GrpSpan": null, "LineSpan": null, "GrpSpanBr": null, "LineSpanBr": null}, "dimension": null, "link": {}, "local": {"GrpSkip": null, "LineSkip": null, "GrpSpan": null, "LineSpan": null}}, {"member": [{"member": [], "type": {"Group": null, "Item": null, "Page": null, "Paragraph": null, "Table": null, "Column": null, "Row": null, "Cell": true, "List": null, "ListItem": null}, "label": "Average", "style": {"Emphasize": true, "Enumerate": null, "ColMajor": null, "RowMajor": null, "GrpSpan": true, "LineSpan": null, "GrpSpanBr": null, "LineSpanBr": null}, "dimension": null, "link": {}, "local": {"GrpSkip": null, "LineSkip": null, "GrpSpan": null, "LineSpan": null}}, {"member": [], "type": {"Group": null, "Item": null, "Page": null, "Paragraph": null, "Table": null, "Column": null, "Row": null, "Cell": true, "List": null, "ListItem": null}, "label": "weight", "style": {"Emphasize": true, "Enumerate": null, "ColMajor": null, "RowMajor": null, "GrpSpan": null, "LineSpan": null, "GrpSpanBr": null, "LineSpanBr": null}, "dimension": null, "link": {}, "local": {"GrpSkip": null, "LineSkip": null, "GrpSpan": null, "LineSpan": null}}, {"member": [], "type": {"Group": null, "Item": null, "Page": null, "Paragraph": null, "Table": null, "Column": null, "Row": null, "Cell": true, "List": null, "ListItem": null}, "label": "0.003", "style": {"Emphasize": null, "Enumerate": null, "ColMajor": null, "RowMajor": null, "GrpSpan": null, "LineSpan": null, "GrpSpanBr": null, "LineSpanBr": null}, "dimension": null, "link": {}, "local": {"GrpSkip": null, "LineSkip": null, "GrpSpan": null, "LineSpan": null}}, {"member": [], "type": {"Group": null, "Item": null, "Page": null, "Paragraph": null, "Table": null, "Column": null, "Row": null, "Cell": true, "List": null, "ListItem": null}, "label": "0.002", "style": {"Emphasize": null, "Enumerate": null, "ColMajor": null, "RowMajor": null, "GrpSpan": null, "LineSpan": null, "GrpSpanBr": null, "LineSpanBr": null}, "dimension": null, "link": {}, "local": {"GrpSkip": null, "LineSkip": null, "GrpSpan": null, "LineSpan": null}}], "type": {"Group": null, "Item": null, "Page": null, "Paragraph": null, "Table": null, "Column": true, "Row": null, "Cell": null, "List": null, "ListItem": null}, "label": null, "style": {"Emphasize": null, "Enumerate": true, "ColMajor": null, "RowMajor": null, "GrpSpan": null, "LineSpan": null, "GrpSpanBr": null, "LineSpanBr": null}, "dimension": null, "link": {}, "local": {"GrpSkip": null, "LineSkip": null, "GrpSpan": null, "LineSpan": null}}, {"member": [{"member": [], "type": {"Group": null, "Item": null, "Page": null, "Paragraph": null, "Table": null, "Column": null, "Row": null, "Cell": true, "List": null, "ListItem": null}, "label": "other\ncategory", "style": {"Emphasize": true, "Enumerate": null, "ColMajor": null, "RowMajor": null, "GrpSpan": null, "LineSpan": true, "GrpSpanBr": null, "LineSpanBr": null}, "dimension": null, "link": {}, "local": {"GrpSkip": null, "LineSkip": null, "GrpSpan": null, "LineSpan": null}}, {"member": [], "type": {"Group": null, "Item": null, "Page": null, "Paragraph": null, "Table": null, "Column": null, "Row": null, "Cell": true, "List": null, "ListItem": null}, "label": "other\ncategory", "style": {"Emphasize": true, "Enumerate": null, "ColMajor": null, "RowMajor": null, "GrpSpan": null, "LineSpan": true, "GrpSpanBr": null, "LineSpanBr": null}, "dimension": null, "link": {}, "local": {"GrpSkip": null, "LineSkip": null, "GrpSpan": null, "LineSpan": null}}], "type": {"Group": null, "Item": null, "Page": null, "Paragraph": null, "Table": null, "Column": true, "Row": null, "Cell": null, "List": null, "ListItem": null}, "label": null, "style": {"Emphasize": null, "Enumerate": true, "ColMajor": null, "RowMajor": null, "GrpSpan": null, "LineSpan": null, "GrpSpanBr": null, "LineSpanBr": null}, "dimension": null, "link": {}, "local": {"GrpSkip": null, "LineSkip": null, "GrpSpan": null, "LineSpan": null}}, {"member": [{"member": [], "type": {"Group": null, "Item": null, "Page": null, "Paragraph": null, "Table": null, "Column": null, "Row": null, "Cell": true, "List": null, "ListItem": null}, "label": "Misc", "style": {"Emphasize": true, "Enumerate": null, "ColMajor": null, "RowMajor": null, "GrpSpan": null, "LineSpan": null, "GrpSpanBr": null, "LineSpanBr": null}, "dimension": null, "link": {}, "local": {"GrpSkip": null, "LineSkip": null, "GrpSpan": null, "LineSpan": null}}], "type": {"Group": null, "Item": null, "Page": null, "Paragraph": null, "Table": null, "Column": true, "Row": null, "Cell": null, "List": null, "ListItem": null}, "label": null, "style": {"Emphasize": null, "Enumerate": true, "ColMajor": null, "RowMajor": null, "GrpSpan": null, "LineSpan": null, "GrpSpanBr": null, "LineSpanBr": null}, "dimension": null, "link": {}, "local": {"GrpSkip": null, "LineSkip": null, "GrpSpan": null, "LineSpan": null}}], "type": {"Group": null, "Item": null, "Page": null, "Paragraph": null, "Table": true, "Column": null, "Row": null, "Cell": null, "List": null, "ListItem": null}, "label": "A test table with merged cells", "style": {"Emphasize": null, "Enumerate": true, "ColMajor": true, "RowMajor": null, "GrpSpan": null, "LineSpan": null, "GrpSpanBr": null, "LineSpanBr": null}, "dimension": 2, "link": {}, "local": {"GrpSkip": null, "LineSkip": null, "GrpSpan": null, "LineSpan": null}}], "type": {"Group": null, "Item": null, "Page": true, "Paragraph": null, "Table": null, "Column": null, "Row": null, "Cell": null, "List": null, "ListItem": null}, "label": "HTML table example on Page 3 of RFC 1942", "style": {"Emphasize": null, "Enumerate": null, "ColMajor": null, "RowMajor": null, "GrpSpan": null, "LineSpan": null, "GrpSpanBr": null, "LineSpanBr": null}, "dimension": null, "link": {}, "local": {"GrpSkip": null, "LineSkip": null, "GrpSpan": null, "LineSpan": null}}